genius_client/__init__.py
genius_client/client.py
genius_client/models.py
genius_client-0.0.1.dist-info/METADATA
genius_client-0.0.1.dist-info/WHEEL
genius_client-0.0.1.dist-info/licenses/LICENSE.txt
genius_client-0.0.1.dist-info/RECORD
