Metadata-Version: 2.1
Name: genius_client
Version: 0.0.1
Summary: A Python SDK for the Genius API
Project-URL: Homepage, https://github.com/ruberVulpes/GeniusClient
Project-URL: Issues, https://github.com/ruberVulpes/GeniusClient/issues
Project-URL: Genius API, https://docs.genius.com
Author-email: William Fox <william@rubervulpes.com>
License: MIT License
License-File: LICENSE.txt
Keywords: API,Genius
Classifier: Development Status :: 4 - Beta
Classifier: Intended Audience :: Developers
Classifier: License :: OSI Approved :: MIT License
Classifier: Programming Language :: Python :: 3
Classifier: Programming Language :: Python :: 3.9
Classifier: Programming Language :: Python :: 3.10
Classifier: Programming Language :: Python :: 3.11
Classifier: Programming Language :: Python :: 3.12
Requires-Python: >=3.9
Requires-Dist: pydantic
Requires-Dist: pytest
Requires-Dist: requests
